crosspy/CMakeLists.txt
crosspy/__init__.py
crosspy/_backend.py
crosspy/context.py
crosspy/core/__init__.py
crosspy/core/creation.py
crosspy/core/ndarray.py
crosspy/core/utils.py
crosspy/core/x1darray.py
crosspy/device/__init__.py
crosspy/device/cpu/__init__.py
crosspy/device/cpu/generic.py
crosspy/device/detail.py
crosspy/device/gpu/__init__.py
crosspy/device/gpu/component.py
crosspy/device/gpu/cuda/__init__.py
crosspy/device/gpu/cuda/cuda_based.py
crosspy/device/gpu/cuda/cupy_based.py
crosspy/device/memory.py
crosspy/device/meta.py
crosspy/dispatcher.py
crosspy/ext/__init__.py
crosspy/ext/numba_support/__init__.py
crosspy/partition/__init__.py
crosspy/partition/ldevice.py
crosspy/partition/placement.py
crosspy/random/__init__.py
crosspy/transfer/__init__.py
crosspy/transfer/cache.py
crosspy/transfer/collective.py
crosspy/utils/CMakeLists.txt
crosspy/utils/__init__.py
crosspy/utils/array.py
crosspy/utils/attr.py
crosspy/utils/construction.py
crosspy/utils/cupy.py
crosspy/utils/devtools.py
crosspy/utils/indexing.py
crosspy/utils/profile/include/Timer.h
crosspy/utils/profile/src/Timer.cpp
crosspy/utils/profile/src/__init__.cpp
crosspy/utils/profile.cpython-39-x86_64-linux-gnu.so
crosspy/utils/wrapper.py
crosspy-0.0.0a3.dev79.dist-info/METADATA
crosspy-0.0.0a3.dev79.dist-info/WHEEL
crosspy-0.0.0a3.dev79.dist-info/entry_points.txt
crosspy-0.0.0a3.dev79.dist-info/licenses/LICENSE
crosspy-0.0.0a3.dev79.dist-info/RECORD
