Metadata-Version: 2.1
Name: crosspy
Version: 0.0.0a3.dev79
Author-Email: Bozhi YOU <youbozhi@cs.utexas.edu>
Classifier: Programming Language :: Python :: 3
Classifier: License :: OSI Approved :: MIT License
Classifier: Operating System :: OS Independent
Requires-Python: >=3.9
Requires-Dist: numpy
Requires-Dist: psutil
License-File: LICENSE
